{
	"song": {
		"player1": "bf",
		"gfVersion": "gf",
		"notes": [
			{
				"sectionNotes": [
					[
						0,
						1,
						0
					],
					[
						500,
						1,
						0
					],
					[
						1000,
						1,
						0
					],
					[
						1500,
						1,
						0
					],
					[
						1625,
						2,
						0
					],
					[
						1750,
						3,
						0
					],
					[
						125,
						0,
						0
					],
					[
						250,
						1,
						0
					],
					[
						625,
						0,
						0
					],
					[
						750,
						1,
						0
					],
					[
						1125,
						2,
						0
					],
					[
						1250,
						1,
						0
					]
				],
				"typeOfSection": 0,
				"lengthInSteps": 16,
				"gfSection": false,
				"altAnim": false,
				"mustHitSection": false,
				"changeBPM": false,
				"bpm": 150
			},
			{
				"sectionNotes": [
					[
						2000,
						1,
						0
					],
					[
						2125,
						0,
						0
					],
					[
						2250,
						1,
						0
					],
					[
						2500,
						1,
						0
					],
					[
						2625,
						3,
						0
					],
					[
						2750,
						1,
						0
					],
					[
						3000,
						0,
						0
					],
					[
						3125,
						2,
						0
					],
					[
						3250,
						0,
						0
					],
					[
						3500,
						3,
						0
					],
					[
						3625,
						2,
						0
					],
					[
						3750,
						3,
						0
					]
				],
				"typeOfSection": 0,
				"lengthInSteps": 16,
				"gfSection": false,
				"altAnim": false,
				"mustHitSection": false,
				"changeBPM": false,
				"bpm": 150
			},
			{
				"sectionNotes": [
					[
						4000,
						1,
						0
					],
					[
						4125,
						3,
						0
					],
					[
						4250,
						1,
						0
					],
					[
						4500,
						1,
						0
					],
					[
						4625,
						3,
						0
					],
					[
						4750,
						1,
						0
					],
					[
						5000,
						2,
						0
					],
					[
						5125,
						0,
						0
					],
					[
						5250,
						2,
						0
					],
					[
						5500,
						2,
						0
					],
					[
						5625,
						0,
						0
					],
					[
						5750,
						3,
						0
					]
				],
				"typeOfSection": 0,
				"lengthInSteps": 16,
				"gfSection": false,
				"altAnim": false,
				"mustHitSection": false,
				"changeBPM": false,
				"bpm": 150
			},
			{
				"sectionNotes": [
					[
						6000,
						0,
						0
					],
					[
						6125,
						3,
						0
					],
					[
						6250,
						0,
						0
					],
					[
						6500,
						0,
						0
					],
					[
						6625,
						3,
						0
					],
					[
						6750,
						0,
						0
					],
					[
						7000,
						1,
						0
					],
					[
						7125,
						2,
						0
					],
					[
						7250,
						0,
						0
					],
					[
						7500,
						1,
						0
					],
					[
						7625,
						2,
						0
					],
					[
						7750,
						1,
						0
					]
				],
				"typeOfSection": 0,
				"lengthInSteps": 16,
				"gfSection": false,
				"altAnim": false,
				"mustHitSection": false,
				"changeBPM": false,
				"bpm": 140
			},
			{
				"sectionNotes": [
					[
						8000,
						1,
						0
					],
					[
						8125,
						0,
						0
					],
					[
						8250,
						1,
						0
					],
					[
						8500,
						1,
						0
					],
					[
						8625,
						0,
						0
					],
					[
						8750,
						1,
						0
					],
					[
						9000,
						1,
						0
					],
					[
						9125,
						0,
						0
					],
					[
						9250,
						1,
						0
					],
					[
						9500,
						1,
						0
					],
					[
						9625,
						0,
						0
					],
					[
						9750,
						1,
						0
					]
				],
				"typeOfSection": 0,
				"lengthInSteps": 16,
				"gfSection": false,
				"altAnim": false,
				"mustHitSection": false,
				"changeBPM": false,
				"bpm": 140
			},
			{
				"sectionNotes": [
					[
						10000,
						1,
						0
					],
					[
						10125,
						2,
						0
					],
					[
						10250,
						0,
						0
					],
					[
						10500,
						1,
						0
					],
					[
						10625,
						2,
						0
					],
					[
						10750,
						3,
						0
					],
					[
						11000,
						0,
						0
					],
					[
						11125,
						2,
						0
					],
					[
						11250,
						3,
						0
					],
					[
						11500,
						3,
						0
					],
					[
						11625,
						2,
						0
					],
					[
						11750,
						0,
						0
					]
				],
				"typeOfSection": 0,
				"lengthInSteps": 16,
				"gfSection": false,
				"altAnim": false,
				"mustHitSection": false,
				"changeBPM": false,
				"bpm": 140
			},
			{
				"sectionNotes": [
					[
						12000,
						1,
						0
					],
					[
						12125,
						0,
						0
					],
					[
						12250,
						3,
						0
					],
					[
						12500,
						1,
						0
					],
					[
						12625,
						0,
						0
					],
					[
						12750,
						3,
						0
					],
					[
						13000,
						2,
						0
					],
					[
						13125,
						3,
						0
					],
					[
						13250,
						2,
						0
					],
					[
						13500,
						2,
						0
					],
					[
						13625,
						3,
						0
					],
					[
						13750,
						2,
						0
					]
				],
				"typeOfSection": 0,
				"lengthInSteps": 16,
				"gfSection": false,
				"altAnim": false,
				"mustHitSection": false,
				"changeBPM": false,
				"bpm": 140
			},
			{
				"sectionNotes": [
					[
						14000,
						1,
						0
					],
					[
						14125,
						0,
						0
					],
					[
						14250,
						1,
						0
					],
					[
						14500,
						1,
						0
					],
					[
						14625,
						2,
						0
					],
					[
						14750,
						0,
						0
					],
					[
						15000,
						3,
						0
					],
					[
						15125,
						0,
						0
					],
					[
						15250,
						1,
						0
					],
					[
						15500,
						0,
						0
					],
					[
						15625,
						2,
						0
					],
					[
						15750,
						0,
						0
					]
				],
				"typeOfSection": 0,
				"lengthInSteps": 16,
				"gfSection": false,
				"altAnim": false,
				"mustHitSection": false,
				"changeBPM": false,
				"bpm": 140
			},
			{
				"sectionNotes": [
					[
						16000,
						1,
						0
					],
					[
						16500,
						1,
						0
					],
					[
						17000,
						1,
						0
					],
					[
						17500,
						1,
						0
					],
					[
						17625,
						2,
						0
					],
					[
						17750,
						3,
						0
					],
					[
						16125,
						0,
						0
					],
					[
						16250,
						1,
						0
					],
					[
						16625,
						0,
						0
					],
					[
						16750,
						1,
						0
					],
					[
						17125,
						2,
						0
					],
					[
						17250,
						1,
						0
					]
				],
				"typeOfSection": 0,
				"lengthInSteps": 16,
				"gfSection": false,
				"altAnim": false,
				"mustHitSection": true,
				"changeBPM": false,
				"bpm": 140
			},
			{
				"sectionNotes": [
					[
						18000,
						1,
						0
					],
					[
						18125,
						0,
						0
					],
					[
						18250,
						1,
						0
					],
					[
						18500,
						1,
						0
					],
					[
						18625,
						3,
						0
					],
					[
						18750,
						1,
						0
					],
					[
						19000,
						0,
						0
					],
					[
						19125,
						2,
						0
					],
					[
						19250,
						0,
						0
					],
					[
						19500,
						3,
						0
					],
					[
						19625,
						2,
						0
					],
					[
						19750,
						3,
						0
					]
				],
				"typeOfSection": 0,
				"lengthInSteps": 16,
				"gfSection": false,
				"altAnim": false,
				"mustHitSection": true,
				"changeBPM": false,
				"bpm": 140
			},
			{
				"sectionNotes": [
					[
						20000,
						1,
						0
					],
					[
						20125,
						3,
						0
					],
					[
						20250,
						1,
						0
					],
					[
						20500,
						1,
						0
					],
					[
						20625,
						3,
						0
					],
					[
						20750,
						1,
						0
					],
					[
						21000,
						2,
						0
					],
					[
						21125,
						0,
						0
					],
					[
						21250,
						2,
						0
					],
					[
						21500,
						2,
						0
					],
					[
						21625,
						0,
						0
					],
					[
						21750,
						3,
						0
					]
				],
				"typeOfSection": 0,
				"lengthInSteps": 16,
				"gfSection": false,
				"altAnim": false,
				"mustHitSection": true,
				"changeBPM": false,
				"bpm": 120
			},
			{
				"sectionNotes": [
					[
						22000,
						0,
						0
					],
					[
						22125,
						3,
						0
					],
					[
						22250,
						0,
						0
					],
					[
						22500,
						0,
						0
					],
					[
						22625,
						3,
						0
					],
					[
						22750,
						0,
						0
					],
					[
						23000,
						1,
						0
					],
					[
						23125,
						2,
						0
					],
					[
						23250,
						0,
						0
					],
					[
						23500,
						1,
						0
					],
					[
						23625,
						2,
						0
					],
					[
						23750,
						1,
						0
					]
				],
				"typeOfSection": 0,
				"lengthInSteps": 16,
				"gfSection": false,
				"altAnim": false,
				"mustHitSection": true,
				"changeBPM": false,
				"bpm": 120
			},
			{
				"sectionNotes": [
					[
						24000,
						1,
						0
					],
					[
						24125,
						0,
						0
					],
					[
						24250,
						1,
						0
					],
					[
						24500,
						1,
						0
					],
					[
						24625,
						0,
						0
					],
					[
						24750,
						1,
						0
					],
					[
						25000,
						1,
						0
					],
					[
						25125,
						0,
						0
					],
					[
						25250,
						1,
						0
					],
					[
						25500,
						1,
						0
					],
					[
						25625,
						0,
						0
					],
					[
						25750,
						1,
						0
					]
				],
				"typeOfSection": 0,
				"lengthInSteps": 16,
				"gfSection": false,
				"altAnim": false,
				"mustHitSection": true,
				"changeBPM": false,
				"bpm": 120
			},
			{
				"sectionNotes": [
					[
						26000,
						1,
						0
					],
					[
						26125,
						2,
						0
					],
					[
						26250,
						0,
						0
					],
					[
						26500,
						1,
						0
					],
					[
						26625,
						2,
						0
					],
					[
						26750,
						3,
						0
					],
					[
						27000,
						0,
						0
					],
					[
						27125,
						2,
						0
					],
					[
						27250,
						3,
						0
					],
					[
						27500,
						3,
						0
					],
					[
						27625,
						2,
						0
					],
					[
						27750,
						0,
						0
					]
				],
				"typeOfSection": 0,
				"lengthInSteps": 16,
				"gfSection": false,
				"altAnim": false,
				"mustHitSection": true,
				"changeBPM": false,
				"bpm": 120
			},
			{
				"sectionNotes": [
					[
						28000,
						1,
						0
					],
					[
						28125,
						0,
						0
					],
					[
						28250,
						3,
						0
					],
					[
						28500,
						1,
						0
					],
					[
						28625,
						0,
						0
					],
					[
						28750,
						3,
						0
					],
					[
						29000,
						2,
						0
					],
					[
						29125,
						3,
						0
					],
					[
						29250,
						2,
						0
					],
					[
						29500,
						2,
						0
					],
					[
						29625,
						3,
						0
					],
					[
						29750,
						2,
						0
					]
				],
				"typeOfSection": 0,
				"lengthInSteps": 16,
				"gfSection": false,
				"altAnim": false,
				"mustHitSection": true,
				"changeBPM": false,
				"bpm": 120
			},
			{
				"sectionNotes": [
					[
						30000,
						1,
						0
					],
					[
						30125,
						0,
						0
					],
					[
						30250,
						1,
						0
					],
					[
						30500,
						1,
						0
					],
					[
						30625,
						2,
						0
					],
					[
						30750,
						0,
						0
					],
					[
						31000,
						3,
						0
					],
					[
						31125,
						0,
						0
					],
					[
						31250,
						1,
						0
					],
					[
						31500,
						0,
						0
					],
					[
						31625,
						2,
						0
					],
					[
						31750,
						0,
						0
					]
				],
				"typeOfSection": 0,
				"lengthInSteps": 16,
				"gfSection": false,
				"altAnim": false,
				"mustHitSection": true,
				"changeBPM": false,
				"bpm": 120
			},
			{
				"sectionNotes": [
					[
						32000,
						1,
						0
					],
					[
						32250,
						2,
						0
					],
					[
						32500,
						1,
						0
					],
					[
						32625,
						0,
						0
					],
					[
						32750,
						3,
						0
					],
					[
						33000,
						1,
						0
					],
					[
						33250,
						1,
						0
					],
					[
						33375,
						0,
						0
					],
					[
						33500,
						3,
						0
					],
					[
						33750,
						0,
						0
					]
				],
				"typeOfSection": 0,
				"lengthInSteps": 16,
				"gfSection": false,
				"altAnim": false,
				"mustHitSection": false,
				"changeBPM": false,
				"bpm": 120
			},
			{
				"sectionNotes": [
					[
						34000,
						0,
						0
					],
					[
						34250,
						3,
						0
					],
					[
						34500,
						0,
						0
					],
					[
						34625,
						2,
						0
					],
					[
						34750,
						0,
						0
					],
					[
						34875,
						2,
						0
					],
					[
						35000,
						1,
						0
					],
					[
						35250,
						0,
						0
					],
					[
						35500,
						2,
						0
					],
					[
						35750,
						3,
						0
					],
					[
						35875,
						1,
						0
					]
				],
				"typeOfSection": 0,
				"lengthInSteps": 16,
				"gfSection": false,
				"altAnim": false,
				"mustHitSection": false,
				"changeBPM": false,
				"bpm": 120
			},
			{
				"sectionNotes": [
					[
						36250,
						1,
						0
					],
					[
						36500,
						2,
						0
					],
					[
						36625,
						1,
						0
					],
					[
						36750,
						3,
						0
					],
					[
						36875,
						2,
						0
					],
					[
						37000,
						1,
						0
					],
					[
						37250,
						2,
						0
					],
					[
						37500,
						3,
						0
					],
					[
						37625,
						2,
						0
					],
					[
						37750,
						1,
						0
					],
					[
						36125,
						0,
						0
					],
					[
						36000,
						3,
						0
					]
				],
				"typeOfSection": 0,
				"lengthInSteps": 16,
				"gfSection": false,
				"altAnim": false,
				"mustHitSection": false,
				"changeBPM": false,
				"bpm": 120
			},
			{
				"sectionNotes": [
					[
						38000,
						1,
						0
					],
					[
						38125,
						3,
						0
					],
					[
						38250,
						2,
						0
					],
					[
						38500,
						1,
						0
					],
					[
						38625,
						0,
						0
					],
					[
						38750,
						1,
						0
					],
					[
						39000,
						0,
						0
					],
					[
						39500,
						2,
						0
					],
					[
						39625,
						0,
						0
					],
					[
						39875,
						2,
						0
					],
					[
						39125,
						1,
						0
					],
					[
						39250,
						2,
						0
					]
				],
				"typeOfSection": 0,
				"lengthInSteps": 16,
				"gfSection": false,
				"altAnim": false,
				"mustHitSection": false,
				"changeBPM": false,
				"bpm": 120
			},
			{
				"sectionNotes": [
					[
						40000,
						1,
						0
					],
					[
						40250,
						2,
						0
					],
					[
						40500,
						1,
						0
					],
					[
						40625,
						0,
						0
					],
					[
						40750,
						3,
						0
					],
					[
						41000,
						1,
						0
					],
					[
						41250,
						1,
						0
					],
					[
						41375,
						0,
						0
					],
					[
						41500,
						3,
						0
					],
					[
						41750,
						0,
						0
					]
				],
				"typeOfSection": 0,
				"lengthInSteps": 16,
				"gfSection": false,
				"altAnim": false,
				"mustHitSection": true,
				"changeBPM": false,
				"bpm": 120
			},
			{
				"sectionNotes": [
					[
						42000,
						0,
						0
					],
					[
						42250,
						3,
						0
					],
					[
						42500,
						0,
						0
					],
					[
						42625,
						2,
						0
					],
					[
						42750,
						0,
						0
					],
					[
						42875,
						2,
						0
					],
					[
						43000,
						1,
						0
					],
					[
						43250,
						0,
						0
					],
					[
						43500,
						2,
						0
					],
					[
						43750,
						3,
						0
					],
					[
						43875,
						1,
						0
					]
				],
				"typeOfSection": 0,
				"lengthInSteps": 16,
				"gfSection": false,
				"altAnim": false,
				"mustHitSection": true,
				"changeBPM": false,
				"bpm": 120
			},
			{
				"sectionNotes": [
					[
						44250,
						1,
						0
					],
					[
						44500,
						2,
						0
					],
					[
						44625,
						1,
						0
					],
					[
						44750,
						3,
						0
					],
					[
						44875,
						2,
						0
					],
					[
						45000,
						1,
						0
					],
					[
						45250,
						2,
						0
					],
					[
						45500,
						3,
						0
					],
					[
						45625,
						2,
						0
					],
					[
						45750,
						1,
						0
					],
					[
						44125,
						0,
						0
					],
					[
						44000,
						3,
						0
					]
				],
				"typeOfSection": 0,
				"lengthInSteps": 16,
				"gfSection": false,
				"altAnim": false,
				"mustHitSection": true,
				"changeBPM": false,
				"bpm": 120
			},
			{
				"sectionNotes": [
					[
						46000,
						1,
						0
					],
					[
						46125,
						3,
						0
					],
					[
						46250,
						2,
						0
					],
					[
						46500,
						1,
						0
					],
					[
						46625,
						0,
						0
					],
					[
						46750,
						1,
						0
					],
					[
						47000,
						0,
						0
					],
					[
						47500,
						2,
						0
					],
					[
						47625,
						0,
						0
					],
					[
						47875,
						2,
						0
					],
					[
						47125,
						1,
						0
					],
					[
						47250,
						2,
						0
					]
				],
				"typeOfSection": 0,
				"lengthInSteps": 16,
				"gfSection": false,
				"altAnim": false,
				"mustHitSection": true,
				"changeBPM": false,
				"bpm": 120
			},
			{
				"sectionNotes": [
					[
						48000,
						1,
						0
					],
					[
						48125,
						2,
						0
					],
					[
						48250,
						1,
						0
					],
					[
						48375,
						2,
						0
					],
					[
						48500,
						1,
						0
					],
					[
						48875,
						1,
						0
					],
					[
						49000,
						2,
						0
					],
					[
						49250,
						2,
						0
					],
					[
						49375,
						3,
						0
					],
					[
						49500,
						0,
						0
					],
					[
						49750,
						1,
						0
					]
				],
				"typeOfSection": 0,
				"lengthInSteps": 16,
				"gfSection": false,
				"altAnim": false,
				"mustHitSection": false,
				"changeBPM": false,
				"bpm": 120
			},
			{
				"sectionNotes": [
					[
						50000,
						1,
						0
					],
					[
						50250,
						2,
						0
					],
					[
						50500,
						1,
						0
					],
					[
						50625,
						3,
						0
					],
					[
						50750,
						2,
						0
					],
					[
						50875,
						3,
						0
					],
					[
						51250,
						2,
						0
					],
					[
						51565.625,
						3,
						0
					],
					[
						51000,
						0,
						0
					],
					[
						51500,
						0,
						0
					],
					[
						51750,
						2,
						0
					]
				],
				"typeOfSection": 0,
				"lengthInSteps": 16,
				"gfSection": false,
				"altAnim": false,
				"mustHitSection": false,
				"changeBPM": false,
				"bpm": 120
			},
			{
				"sectionNotes": [
					[
						52000,
						1,
						0
					],
					[
						52125,
						2,
						0
					],
					[
						52250,
						1,
						0
					],
					[
						52375,
						2,
						0
					],
					[
						52500,
						1,
						0
					],
					[
						52875,
						1,
						0
					],
					[
						53000,
						2,
						0
					],
					[
						53250,
						2,
						0
					],
					[
						53375,
						3,
						0
					],
					[
						53500,
						0,
						0
					],
					[
						53750,
						1,
						0
					]
				],
				"typeOfSection": 0,
				"lengthInSteps": 16,
				"gfSection": false,
				"altAnim": false,
				"mustHitSection": true,
				"changeBPM": false,
				"bpm": 120
			},
			{
				"sectionNotes": [
					[
						54000,
						1,
						0
					],
					[
						54250,
						2,
						0
					],
					[
						54500,
						1,
						0
					],
					[
						54625,
						3,
						0
					],
					[
						54750,
						2,
						0
					],
					[
						54875,
						3,
						0
					],
					[
						55250,
						2,
						0
					],
					[
						55565.625,
						3,
						0
					],
					[
						55000,
						0,
						0
					],
					[
						55500,
						0,
						0
					],
					[
						55750,
						2,
						0
					]
				],
				"typeOfSection": 0,
				"lengthInSteps": 16,
				"gfSection": false,
				"altAnim": false,
				"mustHitSection": true,
				"changeBPM": false,
				"bpm": 120
			},
			{
				"sectionNotes": [
					[
						56000,
						1,
						0
					],
					[
						56250,
						0,
						0
					],
					[
						56500,
						2,
						0
					],
					[
						56750,
						2,
						0
					],
					[
						57000,
						1,
						0
					],
					[
						57125,
						3,
						0
					],
					[
						57250,
						2,
						0
					],
					[
						57500,
						1,
						0
					],
					[
						57625,
						0,
						0
					],
					[
						57750,
						2,
						0
					],
					[
						56125,
						3,
						0
					]
				],
				"typeOfSection": 0,
				"lengthInSteps": 16,
				"gfSection": false,
				"altAnim": false,
				"mustHitSection": false,
				"changeBPM": false,
				"bpm": 120
			},
			{
				"sectionNotes": [
					[
						58000,
						2,
						0
					],
					[
						58250,
						2,
						0
					],
					[
						58500,
						0,
						0
					],
					[
						58750,
						3,
						0
					],
					[
						59000,
						3,
						0
					],
					[
						59125,
						2,
						0
					],
					[
						58625,
						1,
						0
					],
					[
						59500,
						0,
						0
					],
					[
						59625,
						1,
						0
					],
					[
						59750,
						2,
						0
					],
					[
						59875,
						3,
						0
					]
				],
				"typeOfSection": 0,
				"lengthInSteps": 16,
				"gfSection": false,
				"altAnim": false,
				"mustHitSection": false,
				"changeBPM": false,
				"bpm": 120
			},
			{
				"sectionNotes": [
					[
						60000,
						1,
						0
					],
					[
						60250,
						0,
						0
					],
					[
						60500,
						2,
						0
					],
					[
						60750,
						2,
						0
					],
					[
						61000,
						1,
						0
					],
					[
						61125,
						3,
						0
					],
					[
						61250,
						2,
						0
					],
					[
						61500,
						1,
						0
					],
					[
						61625,
						0,
						0
					],
					[
						61750,
						2,
						0
					],
					[
						60125,
						3,
						0
					]
				],
				"typeOfSection": 0,
				"lengthInSteps": 16,
				"gfSection": false,
				"altAnim": false,
				"mustHitSection": true,
				"changeBPM": false,
				"bpm": 120
			},
			{
				"sectionNotes": [
					[
						62000,
						2,
						0
					],
					[
						62250,
						2,
						0
					],
					[
						62500,
						0,
						0
					],
					[
						62750,
						3,
						0
					],
					[
						63000,
						3,
						0
					],
					[
						63125,
						2,
						0
					],
					[
						62625,
						1,
						0
					],
					[
						63500,
						0,
						0
					],
					[
						63625,
						1,
						0
					],
					[
						63750,
						2,
						0
					],
					[
						63875,
						3,
						0
					]
				],
				"typeOfSection": 0,
				"lengthInSteps": 16,
				"gfSection": false,
				"altAnim": false,
				"mustHitSection": true,
				"changeBPM": false,
				"bpm": 120
			},
			{
				"sectionNotes": [
					[
						64000,
						3,
						0
					],
					[
						64250,
						2,
						0
					],
					[
						64500,
						1,
						0
					],
					[
						64625,
						3,
						0
					],
					[
						64750,
						2,
						0
					],
					[
						65000,
						2,
						0
					],
					[
						65125,
						0,
						0
					],
					[
						65500,
						3,
						0
					],
					[
						65625,
						2,
						0
					],
					[
						65750,
						0,
						0
					]
				],
				"typeOfSection": 0,
				"lengthInSteps": 16,
				"gfSection": false,
				"altAnim": false,
				"mustHitSection": false,
				"changeBPM": false,
				"bpm": 120
			},
			{
				"sectionNotes": [
					[
						66000,
						0,
						0
					],
					[
						66125,
						2,
						0
					],
					[
						66375,
						2,
						0
					],
					[
						66500,
						0,
						0
					],
					[
						66625,
						3,
						0
					],
					[
						66750,
						2,
						0
					],
					[
						67000,
						2,
						0
					],
					[
						67125,
						1,
						0
					],
					[
						67250,
						3,
						0
					],
					[
						67500,
						1,
						0
					],
					[
						67625,
						0,
						0
					],
					[
						67750,
						2,
						0
					],
					[
						67875,
						3,
						0
					]
				],
				"typeOfSection": 0,
				"lengthInSteps": 16,
				"gfSection": false,
				"altAnim": false,
				"mustHitSection": false,
				"changeBPM": false,
				"bpm": 120
			},
			{
				"sectionNotes": [
					[
						68000,
						3,
						0
					],
					[
						68250,
						2,
						0
					],
					[
						68500,
						1,
						0
					],
					[
						68625,
						3,
						0
					],
					[
						68750,
						2,
						0
					],
					[
						69000,
						2,
						0
					],
					[
						69125,
						0,
						0
					],
					[
						69500,
						3,
						0
					],
					[
						69625,
						2,
						0
					],
					[
						69750,
						0,
						0
					]
				],
				"typeOfSection": 0,
				"lengthInSteps": 16,
				"gfSection": false,
				"altAnim": false,
				"mustHitSection": true,
				"changeBPM": false,
				"bpm": 120
			},
			{
				"sectionNotes": [
					[
						70000,
						0,
						0
					],
					[
						70125,
						2,
						0
					],
					[
						70375,
						2,
						0
					],
					[
						70500,
						0,
						0
					],
					[
						70625,
						3,
						0
					],
					[
						70750,
						2,
						0
					],
					[
						71000,
						2,
						0
					],
					[
						71125,
						1,
						0
					],
					[
						71250,
						3,
						0
					],
					[
						71500,
						1,
						0
					],
					[
						71625,
						0,
						0
					],
					[
						71750,
						2,
						0
					],
					[
						71875,
						3,
						0
					]
				],
				"typeOfSection": 0,
				"lengthInSteps": 16,
				"gfSection": false,
				"altAnim": false,
				"mustHitSection": true,
				"changeBPM": false,
				"bpm": 120
			},
			{
				"sectionNotes": [
					[
						72000,
						1,
						0
					],
					[
						72125,
						2,
						0
					],
					[
						72375,
						1,
						0
					],
					[
						72500,
						0,
						0
					],
					[
						72625,
						1,
						0
					],
					[
						72875,
						1,
						0
					],
					[
						73500,
						1,
						0
					],
					[
						73000,
						2,
						0
					],
					[
						73250,
						2,
						0
					],
					[
						73625,
						0,
						0
					],
					[
						73750,
						2,
						0
					],
					[
						73875,
						3,
						0
					]
				],
				"typeOfSection": 0,
				"lengthInSteps": 16,
				"gfSection": false,
				"altAnim": false,
				"mustHitSection": false,
				"changeBPM": false,
				"bpm": 120
			},
			{
				"sectionNotes": [
					[
						74250,
						0,
						0
					],
					[
						74500,
						0,
						0
					],
					[
						74750,
						2,
						0
					],
					[
						75000,
						3,
						0
					],
					[
						75125,
						2,
						0
					],
					[
						75250,
						0,
						0
					],
					[
						75500,
						2,
						0
					],
					[
						75625,
						3,
						0
					],
					[
						75750,
						2,
						0
					],
					[
						75875,
						0,
						0
					],
					[
						74000,
						1,
						0
					],
					[
						74125,
						3,
						0
					],
					[
						74625,
						1,
						0
					]
				],
				"typeOfSection": 0,
				"lengthInSteps": 16,
				"gfSection": false,
				"altAnim": false,
				"mustHitSection": false,
				"changeBPM": false,
				"bpm": 120
			},
			{
				"sectionNotes": [
					[
						76000,
						1,
						0
					],
					[
						76125,
						2,
						0
					],
					[
						76375,
						1,
						0
					],
					[
						76500,
						0,
						0
					],
					[
						76625,
						1,
						0
					],
					[
						76875,
						1,
						0
					],
					[
						77500,
						1,
						0
					],
					[
						77000,
						2,
						0
					],
					[
						77250,
						2,
						0
					],
					[
						77625,
						0,
						0
					],
					[
						77750,
						2,
						0
					],
					[
						77875,
						3,
						0
					]
				],
				"typeOfSection": 0,
				"lengthInSteps": 16,
				"gfSection": false,
				"altAnim": false,
				"mustHitSection": true,
				"changeBPM": false,
				"bpm": 120
			},
			{
				"sectionNotes": [
					[
						78250,
						0,
						0
					],
					[
						78500,
						0,
						0
					],
					[
						78750,
						2,
						0
					],
					[
						79000,
						3,
						0
					],
					[
						79125,
						2,
						0
					],
					[
						79250,
						0,
						0
					],
					[
						79500,
						2,
						0
					],
					[
						79625,
						3,
						0
					],
					[
						79750,
						2,
						0
					],
					[
						79875,
						0,
						0
					],
					[
						78000,
						1,
						0
					],
					[
						78125,
						3,
						0
					],
					[
						78625,
						1,
						0
					]
				],
				"typeOfSection": 0,
				"lengthInSteps": 16,
				"gfSection": false,
				"altAnim": false,
				"mustHitSection": true,
				"changeBPM": false,
				"bpm": 120
			},
			{
				"sectionNotes": [
					[
						80000,
						2,
						0
					],
					[
						80250,
						0,
						0
					],
					[
						80375,
						3,
						0
					],
					[
						80500,
						2,
						0
					],
					[
						80750,
						1,
						0
					],
					[
						81000,
						0,
						0
					],
					[
						81125,
						3,
						0
					],
					[
						81250,
						0,
						0
					],
					[
						81375,
						1,
						0
					],
					[
						81500,
						2,
						0
					],
					[
						81750,
						1,
						0
					],
					[
						81875,
						2,
						0
					]
				],
				"typeOfSection": 0,
				"lengthInSteps": 16,
				"gfSection": false,
				"altAnim": false,
				"mustHitSection": false,
				"changeBPM": false,
				"bpm": 120
			},
			{
				"sectionNotes": [
					[
						82000,
						3,
						0
					],
					[
						82125,
						2,
						0
					],
					[
						82250,
						0,
						0
					],
					[
						82500,
						1,
						0
					],
					[
						82750,
						0,
						0
					],
					[
						82875,
						2,
						0
					],
					[
						83000,
						1,
						0
					],
					[
						83125,
						3,
						0
					],
					[
						83375,
						1,
						0
					],
					[
						83500,
						2,
						0
					],
					[
						83750,
						1,
						0
					]
				],
				"typeOfSection": 0,
				"lengthInSteps": 16,
				"gfSection": false,
				"altAnim": false,
				"mustHitSection": false,
				"changeBPM": false,
				"bpm": 120
			},
			{
				"sectionNotes": [
					[
						84000,
						2,
						0
					],
					[
						84250,
						0,
						0
					],
					[
						84375,
						3,
						0
					],
					[
						84500,
						2,
						0
					],
					[
						84750,
						1,
						0
					],
					[
						85000,
						0,
						0
					],
					[
						85125,
						3,
						0
					],
					[
						85250,
						0,
						0
					],
					[
						85375,
						1,
						0
					],
					[
						85500,
						2,
						0
					],
					[
						85750,
						1,
						0
					],
					[
						85875,
						2,
						0
					]
				],
				"typeOfSection": 0,
				"lengthInSteps": 16,
				"gfSection": false,
				"altAnim": false,
				"mustHitSection": true,
				"changeBPM": false,
				"bpm": 120
			},
			{
				"sectionNotes": [
					[
						86000,
						3,
						0
					],
					[
						86125,
						2,
						0
					],
					[
						86250,
						0,
						0
					],
					[
						86500,
						1,
						0
					],
					[
						86750,
						0,
						0
					],
					[
						86875,
						2,
						0
					],
					[
						87000,
						1,
						0
					],
					[
						87125,
						3,
						0
					],
					[
						87375,
						1,
						0
					],
					[
						87500,
						2,
						0
					],
					[
						87750,
						1,
						0
					]
				],
				"typeOfSection": 0,
				"lengthInSteps": 16,
				"gfSection": false,
				"altAnim": false,
				"mustHitSection": true,
				"changeBPM": false,
				"bpm": 120
			},
			{
				"sectionNotes": [
					[
						88000,
						1,
						0
					],
					[
						88000,
						5,
						0
					],
					[
						88125,
						2,
						0
					],
					[
						88125,
						6,
						0
					],
					[
						88250,
						1,
						0
					],
					[
						88250,
						5,
						0
					],
					[
						88500,
						1,
						0
					],
					[
						88500,
						5,
						0
					],
					[
						88625,
						0,
						0
					],
					[
						88750,
						3,
						0
					],
					[
						88750,
						7,
						0
					],
					[
						89000,
						0,
						0
					],
					[
						89000,
						4,
						0
					],
					[
						89250,
						1,
						0
					],
					[
						89250,
						5,
						0
					],
					[
						89500,
						0,
						0
					],
					[
						89500,
						4,
						0
					],
					[
						88625,
						4,
						0
					],
					[
						89625,
						1,
						0
					],
					[
						89750,
						2,
						0
					],
					[
						89875,
						3,
						0
					],
					[
						89625,
						5,
						0
					],
					[
						89750,
						6,
						0
					],
					[
						89875,
						7,
						0
					]
				],
				"typeOfSection": 0,
				"lengthInSteps": 16,
				"gfSection": false,
				"altAnim": false,
				"mustHitSection": false,
				"changeBPM": false,
				"bpm": 120
			},
			{
				"sectionNotes": [
					[
						90000,
						1,
						0
					],
					[
						90000,
						5,
						0
					],
					[
						90187.5,
						3,
						0
					],
					[
						90187.5,
						7,
						0
					],
					[
						90375,
						0,
						0
					],
					[
						90375,
						4,
						0
					],
					[
						90500,
						1,
						0
					],
					[
						90500,
						5,
						0
					],
					[
						90750,
						3,
						0
					],
					[
						90750,
						7,
						0
					],
					[
						91000,
						1,
						0
					],
					[
						91000,
						5,
						0
					],
					[
						91125,
						3,
						0
					],
					[
						91125,
						7,
						0
					],
					[
						91250,
						0,
						0
					],
					[
						91250,
						4,
						0
					],
					[
						91500,
						1,
						0
					],
					[
						91500,
						5,
						0
					],
					[
						91625,
						2,
						0
					],
					[
						91625,
						6,
						0
					],
					[
						91750,
						0,
						0
					],
					[
						91750,
						4,
						0
					]
				],
				"typeOfSection": 0,
				"lengthInSteps": 16,
				"gfSection": false,
				"altAnim": false,
				"mustHitSection": false,
				"changeBPM": false,
				"bpm": 120
			},
			{
				"sectionNotes": [
					[
						92000,
						2,
						0
					],
					[
						92000,
						6,
						0
					],
					[
						92125,
						0,
						0
					],
					[
						92125,
						4,
						0
					],
					[
						92375,
						2,
						0
					],
					[
						92375,
						6,
						0
					],
					[
						92500,
						1,
						0
					],
					[
						92500,
						5,
						0
					],
					[
						92625,
						3,
						0
					],
					[
						92625,
						7,
						0
					],
					[
						92750,
						1,
						0
					],
					[
						92750,
						5,
						0
					],
					[
						93000,
						0,
						0
					],
					[
						93000,
						4,
						0
					],
					[
						93250,
						2,
						0
					],
					[
						93250,
						6,
						0
					],
					[
						93625,
						3,
						0
					],
					[
						93625,
						7,
						0
					],
					[
						93750,
						2,
						0
					],
					[
						93750,
						6,
						0
					],
					[
						93125,
						3,
						0
					],
					[
						93375,
						1,
						0
					],
					[
						93125,
						7,
						0
					],
					[
						93375,
						5,
						0
					]
				],
				"typeOfSection": 0,
				"lengthInSteps": 16,
				"gfSection": false,
				"altAnim": false,
				"mustHitSection": true,
				"changeBPM": false,
				"bpm": 120
			},
			{
				"sectionNotes": [
					[
						94000,
						3,
						0
					],
					[
						94000,
						7,
						0
					],
					[
						94250,
						2,
						0
					],
					[
						94250,
						6,
						0
					],
					[
						94500,
						2,
						0
					],
					[
						94750,
						0,
						0
					],
					[
						94750,
						4,
						0
					],
					[
						95000,
						0,
						0
					],
					[
						95625,
						0,
						0
					],
					[
						95625,
						4,
						0
					],
					[
						95750,
						2,
						0
					],
					[
						95750,
						6,
						0
					],
					[
						94625,
						3,
						0
					],
					[
						94500,
						6,
						0
					],
					[
						94625,
						7,
						0
					],
					[
						95125,
						1,
						0
					],
					[
						95250,
						2,
						0
					],
					[
						95375,
						3,
						0
					],
					[
						95000,
						4,
						0
					],
					[
						95125,
						5,
						0
					],
					[
						95250,
						6,
						0
					],
					[
						95375,
						7,
						0
					]
				],
				"typeOfSection": 0,
				"lengthInSteps": 16,
				"gfSection": false,
				"altAnim": false,
				"mustHitSection": true,
				"changeBPM": false,
				"bpm": 120
			},
			{
				"sectionNotes": [
					[
						96250,
						2,
						0
					],
					[
						96250,
						6,
						0
					],
					[
						96750,
						2,
						0
					],
					[
						96750,
						6,
						0
					],
					[
						97000,
						1,
						0
					],
					[
						97000,
						5,
						0
					],
					[
						97250,
						2,
						0
					],
					[
						97500,
						1,
						0
					],
					[
						97500,
						5,
						0
					],
					[
						97625,
						0,
						0
					],
					[
						97625,
						4,
						0
					],
					[
						97750,
						2,
						0
					],
					[
						97750,
						6,
						0
					],
					[
						96000,
						1,
						0
					],
					[
						96000,
						5,
						0
					],
					[
						96500,
						3,
						0
					],
					[
						96500,
						7,
						0
					],
					[
						97250,
						6,
						0
					]
				],
				"typeOfSection": 0,
				"lengthInSteps": 16,
				"gfSection": false,
				"altAnim": false,
				"mustHitSection": false,
				"changeBPM": false,
				"bpm": 120
			},
			{
				"sectionNotes": [
					[
						98000,
						1,
						0
					],
					[
						98000,
						5,
						0
					],
					[
						98125,
						0,
						0
					],
					[
						98125,
						4,
						0
					],
					[
						98250,
						2,
						0
					],
					[
						98250,
						6,
						0
					],
					[
						98500,
						1,
						0
					],
					[
						98500,
						5,
						0
					],
					[
						98625,
						2,
						0
					],
					[
						98625,
						6,
						0
					],
					[
						98750,
						3,
						0
					],
					[
						98750,
						7,
						0
					],
					[
						99000,
						1,
						0
					],
					[
						99000,
						5,
						0
					],
					[
						99125,
						3,
						0
					],
					[
						99125,
						7,
						0
					],
					[
						99250,
						1,
						0
					],
					[
						99250,
						5,
						0
					],
					[
						99500,
						0,
						0
					],
					[
						99500,
						4,
						0
					],
					[
						99750,
						2,
						0
					],
					[
						99750,
						6,
						0
					]
				],
				"typeOfSection": 0,
				"lengthInSteps": 16,
				"gfSection": false,
				"altAnim": false,
				"mustHitSection": false,
				"changeBPM": false,
				"bpm": 120
			},
			{
				"sectionNotes": [
					[
						100000,
						3,
						0
					],
					[
						100000,
						7,
						0
					],
					[
						100250,
						2,
						0
					],
					[
						100250,
						6,
						0
					],
					[
						100500,
						0,
						0
					],
					[
						100500,
						4,
						0
					],
					[
						100625,
						3,
						0
					],
					[
						100625,
						7,
						0
					],
					[
						101000,
						1,
						0
					],
					[
						101000,
						5,
						0
					],
					[
						100750,
						0,
						0
					],
					[
						100750,
						4,
						0
					],
					[
						101250,
						2,
						0
					],
					[
						101250,
						6,
						0
					],
					[
						101500,
						0,
						0
					],
					[
						101500,
						4,
						0
					],
					[
						101750,
						3,
						0
					],
					[
						101750,
						7,
						0
					]
				],
				"typeOfSection": 0,
				"lengthInSteps": 16,
				"gfSection": false,
				"altAnim": false,
				"mustHitSection": true,
				"changeBPM": false,
				"bpm": 120
			},
			{
				"sectionNotes": [
					[
						102000,
						1,
						0
					],
					[
						102000,
						5,
						0
					],
					[
						102250,
						2,
						0
					],
					[
						102250,
						6,
						0
					],
					[
						102375,
						0,
						0
					],
					[
						102375,
						4,
						0
					],
					[
						102500,
						3,
						0
					],
					[
						102500,
						7,
						0
					],
					[
						102625,
						0,
						0
					],
					[
						102625,
						4,
						0
					],
					[
						102750,
						2,
						0
					],
					[
						102750,
						6,
						0
					],
					[
						103000,
						0,
						0
					],
					[
						103000,
						4,
						0
					],
					[
						103250,
						2,
						0
					],
					[
						103250,
						6,
						0
					],
					[
						103500,
						2,
						0
					],
					[
						103500,
						6,
						0
					],
					[
						103625,
						1,
						0
					],
					[
						103625,
						5,
						0
					],
					[
						103750,
						0,
						0
					],
					[
						103750,
						4,
						0
					],
					[
						103875,
						1,
						0
					],
					[
						103875,
						5,
						0
					]
				],
				"typeOfSection": 0,
				"lengthInSteps": 16,
				"gfSection": false,
				"altAnim": false,
				"mustHitSection": true,
				"changeBPM": false,
				"bpm": 120
			},
			{
				"sectionNotes": [
					[
						104000,
						3,
						0
					],
					[
						104000,
						7,
						0
					]
				],
				"typeOfSection": 0,
				"lengthInSteps": 16,
				"gfSection": false,
				"altAnim": false,
				"mustHitSection": true,
				"changeBPM": false,
				"bpm": 120
			},
			{
				"sectionNotes": [],
				"typeOfSection": 0,
				"lengthInSteps": 16,
				"gfSection": false,
				"altAnim": false,
				"mustHitSection": true,
				"changeBPM": false,
				"bpm": 120
			},
			{
				"sectionNotes": [],
				"typeOfSection": 0,
				"lengthInSteps": 16,
				"gfSection": false,
				"altAnim": false,
				"mustHitSection": true,
				"changeBPM": false,
				"bpm": 120
			},
			{
				"sectionNotes": [],
				"typeOfSection": 0,
				"lengthInSteps": 16,
				"gfSection": false,
				"altAnim": false,
				"mustHitSection": true,
				"changeBPM": false,
				"bpm": 120
			},
			{
				"lengthInSteps": 16,
				"typeOfSection": 0,
				"sectionNotes": [],
				"altAnim": false,
				"gfSection": false,
				"bpm": 120,
				"changeBPM": false,
				"mustHitSection": true
			},
			{
				"lengthInSteps": 16,
				"typeOfSection": 0,
				"sectionNotes": [],
				"altAnim": false,
				"gfSection": false,
				"bpm": 120,
				"changeBPM": false,
				"mustHitSection": true
			},
			{
				"lengthInSteps": 16,
				"typeOfSection": 0,
				"sectionNotes": [],
				"altAnim": false,
				"gfSection": false,
				"bpm": 120,
				"changeBPM": false,
				"mustHitSection": true
			},
			{
				"lengthInSteps": 16,
				"typeOfSection": 0,
				"sectionNotes": [],
				"altAnim": false,
				"gfSection": false,
				"bpm": 120,
				"changeBPM": false,
				"mustHitSection": true
			},
			{
				"lengthInSteps": 16,
				"typeOfSection": 0,
				"sectionNotes": [],
				"altAnim": false,
				"gfSection": false,
				"bpm": 120,
				"changeBPM": false,
				"mustHitSection": true
			},
			{
				"sectionNotes": [],
				"typeOfSection": 0,
				"lengthInSteps": 16,
				"gfSection": false,
				"altAnim": false,
				"mustHitSection": true,
				"changeBPM": false,
				"bpm": 120
			},
			{
				"gfSection": false,
				"lengthInSteps": 16,
				"altAnim": false,
				"typeOfSection": 0,
				"sectionNotes": [],
				"bpm": 120,
				"changeBPM": false,
				"mustHitSection": true
			}
		],
		"events": [
			[
				0,
				[
					[
						"LinearSpin",
						"110",
						"39600"
					]
				]
			]
		],
		"player2": "saturn",
		"player3": null,
		"splashSkin": "noteSplashes",
		"song": "Halo-Gram",
		"needsVoices": true,
		"arrowSkin": "",
		"validScore": true,
		"stage": "space saturn",
		"bpm": 120,
		"speed": 1.7
	}
}