{
	"animations": [
		{
			"offsets": [
				0,
				0
			],
			"loop": false,
			"fps": 16,
			"anim": "idle",
			"indices": [],
			"name": "split pluto idle"
		},
		{
			"offsets": [
				0,
				0
			],
			"loop": false,
			"fps": 16,
			"anim": "singLEFT",
			"indices": [],
			"name": "split pluto left"
		},
		{
			"offsets": [
				0,
				0
			],
			"loop": false,
			"fps": 16,
			"anim": "singDOWN",
			"indices": [],
			"name": "split pluto down"
		},
		{
			"offsets": [
				0,
				0
			],
			"loop": false,
			"fps": 16,
			"anim": "singUP",
			"indices": [],
			"name": "split pluto up"
		},
		{
			"offsets": [
				0,
				0
			],
			"loop": false,
			"fps": 16,
			"anim": "singRIGHT",
			"indices": [],
			"name": "split pluto right"
		}
	],
	"no_antialiasing": false,
	"image": "characters/split pluto",
	"position": [
		0,
		0
	],
	"healthicon": "pluto",
	"flip_x": true,
	"healthbar_colors": [
		150,
		115,
		70
	],
	"camera_position": [
		0,
		0
	],
	"sing_duration": 6.1,
	"scale": 1
}